{
  "analysis_date": "2025-11-13T22:18:56.530747",
  "portfolio_returns": {
    "BA": {
      "current_price": 194.58,
      "total_value": 5837.4,
      "asset_type": "stock",
      "returns": {
        "previous_trading_day": -0.47,
        "week_to_date": -0.02,
        "month_to_date": -3.2,
        "year_to_date": 9.93,
        "past_30_trading_days": -10.36,
        "past_250_trading_days": 39.02
      }
    },
    "CASH": {
      "current_price": 1.0,
      "total_value": 54174.0,
      "asset_type": "cash",
      "returns": {
        "previous_trading_day": 0.0,
        "week_to_date": 0.0,
        "month_to_date": 0.0,
        "year_to_date": 0.0,
        "past_30_trading_days": 0.0,
        "past_250_trading_days": 0.0
      }
    },
    "HSBC": {
      "current_price": 73.16,
      "total_value": 7316.0,
      "asset_type": "stock",
      "returns": {
        "previous_trading_day": -0.45,
        "week_to_date": 2.65,
        "month_to_date": 5.14,
        "year_to_date": 56.15,
        "past_30_trading_days": 4.54,
        "past_250_trading_days": 71.62
      }
    },
    "HSBC_2025-11-28_67_CALL": {
      "current_price": 6.0,
      "total_value": 1200.0,
      "asset_type": "option",
      "returns": {
        "previous_trading_day": 0.0,
        "week_to_date": null,
        "month_to_date": null,
        "year_to_date": null,
        "past_30_trading_days": null,
        "past_250_trading_days": null
      }
    },
    "JD": {
      "current_price": 30.71,
      "total_value": 6142.0,
      "asset_type": "stock",
      "returns": {
        "previous_trading_day": -1.73,
        "week_to_date": -3.4,
        "month_to_date": -7.05,
        "year_to_date": -8.81,
        "past_30_trading_days": -13.83,
        "past_250_trading_days": -11.42
      }
    },
    "META": {
      "current_price": 609.89,
      "total_value": 12197.8,
      "asset_type": "stock",
      "returns": {
        "previous_trading_day": 0.14,
        "week_to_date": -1.9,
        "month_to_date": -5.93,
        "year_to_date": 4.41,
        "past_30_trading_days": -17.96,
        "past_250_trading_days": 5.48
      }
    },
    "MYO": {
      "current_price": 0.81,
      "total_value": 2021.0,
      "asset_type": "stock",
      "returns": {
        "previous_trading_day": -4.71,
        "week_to_date": -5.15,
        "month_to_date": -12.53,
        "year_to_date": -87.42,
        "past_30_trading_days": -14.47,
        "past_250_trading_days": -82.84
      }
    },
    "NVO": {
      "current_price": 49.16,
      "total_value": 19664.0,
      "asset_type": "stock",
      "returns": {
        "previous_trading_day": -2.19,
        "week_to_date": 7.62,
        "month_to_date": -0.61,
        "year_to_date": -41.93,
        "past_30_trading_days": -11.42,
        "past_250_trading_days": -53.28
      }
    },
    "TXN": {
      "current_price": 162.23,
      "total_value": 17845.3,
      "asset_type": "stock",
      "returns": {
        "previous_trading_day": -0.53,
        "week_to_date": 1.05,
        "month_to_date": 0.48,
        "year_to_date": -10.67,
        "past_30_trading_days": -10.67,
        "past_250_trading_days": -18.58
      }
    },
    "UNH": {
      "current_price": 332.52,
      "total_value": 13300.8,
      "asset_type": "stock",
      "returns": {
        "previous_trading_day": -1.93,
        "week_to_date": 2.56,
        "month_to_date": -2.65,
        "year_to_date": -33.1,
        "past_30_trading_days": -3.67,
        "past_250_trading_days": -43.93
      }
    }
  }
}