{
  "analysis_date": "2026-02-10T22:38:04.402193",
  "portfolio_returns": {
    "ADBE": {
      "current_price": 264.67,
      "total_value": 42347.2,
      "asset_type": "stock",
      "returns": {
        "previous_trading_day": -0.84,
        "week_to_date": -1.38,
        "month_to_date": -9.75,
        "year_to_date": -24.38,
        "past_30_trading_days": -25.19,
        "past_250_trading_days": -41.33
      }
    },
    "ASML": {
      "current_price": 1413.62,
      "total_value": 132411.52,
      "asset_type": "stock",
      "returns": {
        "previous_trading_day": -1.11,
        "week_to_date": 0.04,
        "month_to_date": -0.66,
        "year_to_date": 32.13,
        "past_30_trading_days": 31.78,
        "past_250_trading_days": 91.8
      }
    },
    "BRK.B": {
      "current_price": 500.3,
      "total_value": 61036.6,
      "asset_type": "stock",
      "returns": {
        "previous_trading_day": 0.45,
        "week_to_date": -1.53,
        "month_to_date": 4.11,
        "year_to_date": -0.47,
        "past_30_trading_days": 0.4,
        "past_250_trading_days": 6.41
      }
    },
    "GOOGL": {
      "current_price": 318.58,
      "total_value": 274465.72,
      "asset_type": "stock",
      "returns": {
        "previous_trading_day": -1.77,
        "week_to_date": -1.33,
        "month_to_date": -5.75,
        "year_to_date": 1.78,
        "past_30_trading_days": 1.62,
        "past_250_trading_days": 71.52
      }
    },
    "MCD": {
      "current_price": 325.97,
      "total_value": 35856.7,
      "asset_type": "stock",
      "returns": {
        "previous_trading_day": 0.11,
        "week_to_date": -0.36,
        "month_to_date": 3.48,
        "year_to_date": 6.66,
        "past_30_trading_days": 4.92,
        "past_250_trading_days": 8.16
      }
    },
    "NVDA_2027-06-17_170_CALL": {
      "current_price": 54.6,
      "total_value": 5460.0,
      "asset_type": "option",
      "returns": {
        "previous_trading_day": -1.1,
        "week_to_date": 5.81,
        "month_to_date": -3.84,
        "year_to_date": 0.83,
        "past_30_trading_days": -3.94,
        "past_250_trading_days": null
      }
    },
    "NVDA_2027-12-17_100_CALL": {
      "current_price": 104.25,
      "total_value": 10425.0,
      "asset_type": "option",
      "returns": {
        "previous_trading_day": -1.89,
        "week_to_date": 3.37,
        "month_to_date": -1.42,
        "year_to_date": 1.61,
        "past_30_trading_days": -3.51,
        "past_250_trading_days": null
      }
    },
    "V": {
      "current_price": 328.17,
      "total_value": 48985.94,
      "asset_type": "stock",
      "returns": {
        "previous_trading_day": 0.8,
        "week_to_date": -1.03,
        "month_to_date": 1.97,
        "year_to_date": -6.43,
        "past_30_trading_days": -7.56,
        "past_250_trading_days": -5.9
      }
    },
    "VOO": {
      "current_price": 636.44,
      "total_value": 74476.21,
      "asset_type": "stock",
      "returns": {
        "previous_trading_day": -0.28,
        "week_to_date": 0.19,
        "month_to_date": 0.03,
        "year_to_date": 1.48,
        "past_30_trading_days": 0.25,
        "past_250_trading_days": 15.84
      }
    }
  }
}