{
  "analysis_date": "2026-01-20T16:13:18.240202",
  "portfolio_returns": {
    "ADBE": {
      "current_price": 289.83,
      "total_value": 37678.55,
      "asset_type": "stock",
      "returns": {
        "previous_trading_day": -2.12,
        "week_to_date": -2.12,
        "month_to_date": -17.19,
        "year_to_date": -17.19,
        "past_30_trading_days": -16.3,
        "past_250_trading_days": -32.6
      }
    },
    "ASML": {
      "current_price": 1339.21,
      "total_value": 125441.66,
      "asset_type": "stock",
      "returns": {
        "previous_trading_day": -1.43,
        "week_to_date": -1.43,
        "month_to_date": 25.18,
        "year_to_date": 25.18,
        "past_30_trading_days": 21.81,
        "past_250_trading_days": 78.76
      }
    },
    "BRK.B": {
      "current_price": 487.88,
      "total_value": 59520.75,
      "asset_type": "stock",
      "returns": {
        "previous_trading_day": -1.1,
        "week_to_date": -1.1,
        "month_to_date": -2.94,
        "year_to_date": -2.94,
        "past_30_trading_days": -3.26,
        "past_250_trading_days": 4.26
      }
    },
    "GOOGL": {
      "current_price": 326.85,
      "total_value": 281586.25,
      "asset_type": "stock",
      "returns": {
        "previous_trading_day": -0.95,
        "week_to_date": -0.95,
        "month_to_date": 4.42,
        "year_to_date": 4.42,
        "past_30_trading_days": 1.8,
        "past_250_trading_days": 67.41
      }
    },
    "MCD": {
      "current_price": 304.41,
      "total_value": 41230.81,
      "asset_type": "stock",
      "returns": {
        "previous_trading_day": -0.98,
        "week_to_date": -0.98,
        "month_to_date": -0.4,
        "year_to_date": -0.4,
        "past_30_trading_days": -2.19,
        "past_250_trading_days": 10.88
      }
    },
    "NVDA_2027-06-17_170_CALL": {
      "current_price": 49.1,
      "total_value": 4910.0,
      "asset_type": "option",
      "returns": {
        "previous_trading_day": -5.58,
        "week_to_date": -5.58,
        "month_to_date": -9.33,
        "year_to_date": -9.33,
        "past_30_trading_days": -3.82,
        "past_250_trading_days": null
      }
    },
    "NVDA_2027-12-17_100_CALL": {
      "current_price": 97.5,
      "total_value": 9750.0,
      "asset_type": "option",
      "returns": {
        "previous_trading_day": -5.61,
        "week_to_date": -5.61,
        "month_to_date": -6.79,
        "year_to_date": -6.79,
        "past_30_trading_days": -2.6,
        "past_250_trading_days": null
      }
    },
    "V": {
      "current_price": 326.93,
      "total_value": 48800.68,
      "asset_type": "stock",
      "returns": {
        "previous_trading_day": -0.42,
        "week_to_date": -0.42,
        "month_to_date": -6.78,
        "year_to_date": -6.78,
        "past_30_trading_days": -1.3,
        "past_250_trading_days": 3.01
      }
    },
    "VOO": {
      "current_price": 629.3,
      "total_value": 73640.59,
      "asset_type": "stock",
      "returns": {
        "previous_trading_day": -1.07,
        "week_to_date": -1.07,
        "month_to_date": 0.35,
        "year_to_date": 0.35,
        "past_30_trading_days": 0.1,
        "past_250_trading_days": 15.94
      }
    }
  }
}